djsingleton/__init__.py
djsingleton/admin.py
djsingleton/apps.py
djsingleton/models.py
djsingleton/templatetags/__init__.py
djsingleton/templatetags/djsingleton.py
tests/__init__.py
tests/models.py
tests/settings.py
tests/tests.py
tests/urls.py
tests/wsgi.py
djsingleton-1.1.0.dist-info/LICENSE
djsingleton-1.1.0.dist-info/METADATA
djsingleton-1.1.0.dist-info/WHEEL
djsingleton-1.1.0.dist-info/top_level.txt
djsingleton-1.1.0.dist-info/RECORD
